drongo/__init__.py
drongo/auth/__init__.py
drongo/auth/api.py
drongo/auth/app.py
drongo/auth/endpoint.py
drongo/auth/middleware.py
drongo/auth/module.py
drongo/auth/backends/__init__.py
drongo/auth/backends/_postgres/__init__.py
drongo/auth/backends/_postgres/models.py
drongo/auth/backends/_postgres/services.py
drongo_client/__init__.py
drongo_client/auth.py
drongopy_auth_client-0.0.8.dist-info/LICENSE
drongopy_auth_client-0.0.8.dist-info/METADATA
drongopy_auth_client-0.0.8.dist-info/WHEEL
drongopy_auth_client-0.0.8.dist-info/top_level.txt
drongopy_auth_client-0.0.8.dist-info/zip-safe
drongopy_auth_client-0.0.8.dist-info/RECORD
